mlstream/__init__.py
mlstream/datasets.py
mlstream/datautils.py
mlstream/experiment.py
mlstream/scaling.py
mlstream/utils.py
mlstream/models/__init__.py
mlstream/models/base_models.py
mlstream/models/lstm.py
mlstream/models/nseloss.py
mlstream/models/sklearn_models.py
mlstream/models/xgboost.py
mlstream-0.1.2.dist-info/LICENSE
mlstream-0.1.2.dist-info/METADATA
mlstream-0.1.2.dist-info/WHEEL
mlstream-0.1.2.dist-info/top_level.txt
mlstream-0.1.2.dist-info/RECORD
