Metadata-Version: 2.1
Name: mlstream
Version: 0.1.2
Summary: Machine learning for streamflow prediction
Home-page: http://github.com/gauchm/mlstream
Author: Martin Gauch
Author-email: martin.gauch@uwaterloo.ca
License: Apache-2.0
Keywords: ml hydrology streamflow machine learning
Platform: UNKNOWN
Requires-Dist: pandas
Requires-Dist: numpy
Requires-Dist: h5py
Requires-Dist: tqdm
Requires-Dist: netCDF4
Requires-Dist: numba
Requires-Dist: scipy
Requires-Dist: torch
